pass_client/__init__.py
pass_client/async_client.py
pass_client/client.py
pass_client/exceptions.py
pass_client/models.py
pass_client/py.typed
pass_client-0.1.0.dist-info/METADATA
pass_client-0.1.0.dist-info/WHEEL
pass_client-0.1.0.dist-info/licenses/LICENSE
pass_client-0.1.0.dist-info/RECORD
