Metadata-Version: 2.4
Name: pass-client
Version: 0.1.0
Summary: Typed Python API client for pass (Unix password store)
Project-URL: Homepage, https://github.com/pdubbbbbs/pass-client
Project-URL: Repository, https://github.com/pdubbbbbs/pass-client
Author-email: Philip Wright <philip@alwaysunder.com>
License-Expression: MIT
License-File: LICENSE
Keywords: gpg,pass,password,password-store,security
Classifier: Development Status :: 4 - Beta
Classifier: Intended Audience :: Developers
Classifier: License :: OSI Approved :: MIT License
Classifier: Operating System :: MacOS
Classifier: Operating System :: POSIX :: Linux
Classifier: Programming Language :: Python :: 3
Classifier: Programming Language :: Python :: 3.10
Classifier: Programming Language :: Python :: 3.11
Classifier: Programming Language :: Python :: 3.12
Classifier: Topic :: Security
Classifier: Typing :: Typed
Requires-Python: >=3.10
Provides-Extra: dev
Requires-Dist: mypy>=1.0; extra == 'dev'
Requires-Dist: pytest-asyncio>=0.23; extra == 'dev'
Requires-Dist: pytest-cov>=4.0; extra == 'dev'
Requires-Dist: pytest>=7.0; extra == 'dev'
Requires-Dist: ruff>=0.1; extra == 'dev'
